db_scheduler/__init__.py
db_scheduler/abc.py
db_scheduler/base.py
db_scheduler/errors.py
db_scheduler/py.typed
db_scheduler/timer.py
db_scheduler-0.1.4.dist-info/LICENSE
db_scheduler-0.1.4.dist-info/METADATA
db_scheduler-0.1.4.dist-info/WHEEL
db_scheduler-0.1.4.dist-info/top_level.txt
db_scheduler-0.1.4.dist-info/RECORD
